<?xml version="1.0" encoding="utf-8"?>
<search>
  
  
  
  <entry>
    <title>我的OCR之路</title>
    <link href="/weilai.github.io/2023/08/01/paddle_ocr/"/>
    <url>/weilai.github.io/2023/08/01/paddle_ocr/</url>
    
    <content type="html"><![CDATA[<p><img src="../img/DB%E7%BD%91%E7%BB%9C%E7%BB%93%E6%9E%84%E5%9B%BE.png" alt=""></p><p>简单解释一哈上面的深度学习结构图：</p><p><span style="color:red">输入的图像经过网络Backbone和FPN提取特征，提取后的特征级联在一起，得到原图四分之一大小的特征，然后利用卷积层分别得到文本区域预测概率图和阈值图，进而通过DB的后处理得到文本包围曲线。</span></p><p>各种backbone的对应的图<br><img src="../img/backbone.png" alt=""></p><div class="note note-success">            <p>1、首先对于detect部分我打算进行一个再训练（不改结构，但是换backbone，因为)，比如提高它的感受野，或者改变学习率等。</p><p>目前打算采用<strong>res2net50</strong>来训练，paddle开源了预训练模型，我目前想法是在这个基础上进行训练和调优。</p><p>2、对于识别部分，我打算用自定义的网络结构去进行迁移学习和优化，迁移学习，也就是先用通用数据集，将模型训练到一定程度，然后，接着使用一些独特的数据集进行训练来进行。</p><p>3、对于方向分类器，采用paddle里面的方法，用来处理倾斜图片的方法。</p><p>4、视工作量，添加是否要进行版面结构分析功能，也就是自动提取关键文字内容。</p><p>5、最麻烦的就是将前面训练出来的模型用paddle的工具将其导出成为推理模型，</p>          </div><figure class="highlight python"><table><tr><td class="gutter"><pre><span class="line">1</span><br><span class="line">2</span><br><span class="line">3</span><br><span class="line">4</span><br><span class="line">5</span><br><span class="line">6</span><br><span class="line">7</span><br><span class="line">8</span><br><span class="line">9</span><br><span class="line">10</span><br><span class="line">11</span><br><span class="line">12</span><br><span class="line">13</span><br><span class="line">14</span><br><span class="line">15</span><br><span class="line">16</span><br><span class="line">17</span><br><span class="line">18</span><br><span class="line">19</span><br><span class="line">20</span><br><span class="line">21</span><br><span class="line">22</span><br><span class="line">23</span><br><span class="line">24</span><br><span class="line">25</span><br><span class="line">26</span><br><span class="line">27</span><br><span class="line">28</span><br><span class="line">29</span><br><span class="line">30</span><br><span class="line">31</span><br><span class="line">32</span><br><span class="line">33</span><br><span class="line">34</span><br><span class="line">35</span><br><span class="line">36</span><br><span class="line">37</span><br><span class="line">38</span><br><span class="line">39</span><br><span class="line">40</span><br><span class="line">41</span><br><span class="line">42</span><br><span class="line">43</span><br></pre></td><td class="code"><pre><code class="hljs python">  <span class="hljs-keyword">class</span> <span class="hljs-title class_">ConvBNLayer</span>(nn.Layer):<span class="hljs-comment">#线性层</span><br><span class="hljs-keyword">def</span> <span class="hljs-title function_">__init__</span>(<span class="hljs-params"></span><br><span class="hljs-params">        self,</span><br><span class="hljs-params">        in_channels,</span><br><span class="hljs-params">        out_channels,</span><br><span class="hljs-params">        kernel_size,</span><br><span class="hljs-params">        stride=<span class="hljs-number">1</span>,</span><br><span class="hljs-params">        groups=<span class="hljs-number">1</span>,</span><br><span class="hljs-params">        is_vd_mode=<span class="hljs-literal">False</span>,</span><br><span class="hljs-params">        act=<span class="hljs-literal">None</span>,</span><br><span class="hljs-params">        name=<span class="hljs-literal">None</span>, </span>):<br>    <span class="hljs-built_in">super</span>(ConvBNLayer, self).__init__()<br><br>    self.is_vd_mode = is_vd_mode<br>    self._pool2d_avg = nn.AvgPool2D(<br>        kernel_size=stride, stride=stride, padding=<span class="hljs-number">0</span>, ceil_mode=<span class="hljs-literal">True</span>)<span class="hljs-comment">#平均池化层</span><br>    self._conv = nn.Conv2D(<br>        in_channels=in_channels,<br>        out_channels=out_channels,<br>        kernel_size=kernel_size,<br>        stride=<span class="hljs-number">1</span> <span class="hljs-keyword">if</span> is_vd_mode <span class="hljs-keyword">else</span> stride,<br>        padding=(kernel_size - <span class="hljs-number">1</span>) // <span class="hljs-number">2</span>,<br>        groups=groups,<br>        weight_attr=ParamAttr(name=name + <span class="hljs-string">"_weights"</span>),<br>        bias_attr=<span class="hljs-literal">False</span>)<span class="hljs-comment">#实现二维卷积</span><br>    <span class="hljs-keyword">if</span> name == <span class="hljs-string">"conv1"</span>:<br>        bn_name = <span class="hljs-string">"bn_"</span> + name<br>    <span class="hljs-keyword">else</span>:<br>        bn_name = <span class="hljs-string">"bn"</span> + name[<span class="hljs-number">3</span>:]<br>    self._batch_norm = nn.BatchNorm(<br>        out_channels,<br>        act=act,<br>        param_attr=ParamAttr(name=bn_name + <span class="hljs-string">'_scale'</span>),<br>        bias_attr=ParamAttr(bn_name + <span class="hljs-string">'_offset'</span>),<br>        moving_mean_name=bn_name + <span class="hljs-string">'_mean'</span>,<br>        moving_variance_name=bn_name + <span class="hljs-string">'_variance'</span>)<br><br><span class="hljs-keyword">def</span> <span class="hljs-title function_">forward</span>(<span class="hljs-params">self, inputs</span>):<span class="hljs-comment">#前向反馈</span><br>    <span class="hljs-keyword">if</span> self.is_vd_mode:<br>        inputs = self._pool2d_avg(inputs)<br>    y = self._conv(inputs)<br>    y = self._batch_norm(y)<br>    <span class="hljs-keyword">return</span> y     <br></code></pre></td></tr></table></figure><p>nn.AvgPool2D有以下几个参数：<br>kernel_size：池化核大小，可以是一个整数或一个元组（Tuple），表示池化核的高度和宽度。<br>stride：池化步长，可以是一个整数或一个元组，表示池化核在输入特征图上移动的步长。默认为None，表示步长等于池化核大小。<br>padding：填充大小，可以是一个整数或一个元组，表示在输入特征图的边缘添加的零填充的大小。默认为0，表示不添加填充。<br>ceil_mode：是否使用向上取整模式，默认为False。如果为True，则在计算输出特征图的大小时，使用向上取整的方式；如果为False，则使用向下取整的方式。<br>count_include_pad：是否在计算平均值时包含填充值，默认为True。如果为True，则在求平均值时，将填充值也纳入计算；如果为False，则在求平均值时，忽略填充值。<br>divisor_override：是否使用自定义除数，默认为None。如果不为None，则使用该值作为除数来计算平均值；如果为None，则使用池化核的大小或有效区域的大小作为除数来计算平均值。<br>nn.AvgPool2D有以下一个方法：<br>forward(x)：根据给定的参数对输入特征图x进行平均池化操作，并返回输出特征图y。</p><p>nn.Conv2D有以下几个参数：<br>in_channels：输入通道数。<br>out_channels：输出通道数。<br>kernel_size：卷积核大小，可以是一个整数或一个元组，表示卷积核的高度和宽度。<br>stride：卷积步长，可以是一个整数或一个元组，表示卷积核在输入特征图上移动的步长。默认为1。<br>padding：填充大小，可以是一个整数或一个元组，表示在输入特征图的边缘添加的零填充的大小。默认为0，表示不添加填充。<br>dilation：空洞大小，可以是一个整数或一个元组，表示在卷积核中每个元素之间插入的空洞的大小。默认为1，表示不添加空洞。<br>groups：卷积分组数，默认为1。如果大于1，则将输入通道和输出通道分成相等的组数，每个组内进行独立的卷积操作。<br>weight_attr：权重参数的属性设置，可以是一个ParamAttr对象或者None。默认为None，表示使用默认的初始化方法和正则化方法。<br>bias_attr：偏置参数的属性设置，可以是一个ParamAttr对象、False或者None。默认为None，表示使用默认的初始化方法和正则化方法。如果为False，则不使用偏置参数。</p><p>nn.BatchNorm是一种神经网络层，用于对每个小批量数据的输入进行归一化，使其具有零均值和单位方差。这样可以加速神经网络的训练，提高收敛速度和稳定性。</p><div class="note note-light">            <p>ResNet_vd是一种基于ResNet的改进网络架构，由百度视觉技术部门提出，用于图像分类和目标检测等任务。ResNet_vd的主要改进有以下几点：</p><ul><li>在每个卷积层之前增加了一个批归一化层（Batch Normalization Layer），以减少内部协变量偏移（Internal Covariate Shift），加速网络的收敛，提高网络的泛化能力。</li><li>在每个残差块（Residual Block）的第一个卷积层之前增加了一个平均池化层（Average Pooling Layer），以减少计算量和内存消耗，同时保留特征图的主要信息。</li><li>在每个残差块的最后一个卷积层之后增加了一个激活函数（Activation Function），以增强特征图的非线性表达能力，提高网络的性能。</li></ul>          </div><p>​       配置paddleocr的过程：</p><p>1、创建paddleocr的环境，python==3.7;</p><p>2、克隆仓库，git clone <a href="https://gitee.com/paddlepaddle/PaddleOCR">https://gitee.com/paddlepaddle/PaddleOCR</a></p><p>3、安装依赖包</p><p>pip install paddleocr -i <a href="https://pypi.tuna.tsinghua.edu.cn/simple">https://pypi.tuna.tsinghua.edu.cn/simple</a></p><p>python -m pip install paddlepaddle==2.2.2 -i <a href="https://pypi.tuna.tsinghua.edu.cn/simple">https://pypi.tuna.tsinghua.edu.cn/simple</a></p><p>因为urllib3&gt;2.0的话，就需要openssll1.1.0以上的版本支持。所以重新安装urllib3</p><p>pip install urllib3==1.25.6  -i <a href="https://pypi.tuna.tsinghua.edu.cn/simple">https://pypi.tuna.tsinghua.edu.cn/simple</a></p><p>​</p>]]></content>
    
    
    
  </entry>
  
  
  
  <entry>
    <title>有影响力的沟通的嘉宾发言记录</title>
    <link href="/weilai.github.io/2023/07/21/%E6%9C%89%E5%BD%B1%E5%93%8D%E5%8A%9B%E7%9A%84%E6%B2%9F%E9%80%9A%E7%9A%84%E5%98%89%E5%AE%BE%E8%AE%B0%E5%BD%95/"/>
    <url>/weilai.github.io/2023/07/21/%E6%9C%89%E5%BD%B1%E5%93%8D%E5%8A%9B%E7%9A%84%E6%B2%9F%E9%80%9A%E7%9A%84%E5%98%89%E5%AE%BE%E8%AE%B0%E5%BD%95/</url>
    
    <content type="html"><![CDATA[<h2 id="第一期的嘉宾-kiki">第一期的嘉宾  kiki</h2><h3 id="嘉宾简介：">嘉宾简介：</h3><div class="note note-success">            <p>KiKe是  join Wealth Management Generalist Program at RBC<br>RBC 财富管理通才计划是一项独特的轮岗计划，旨在培养 RBC 财富和资产管理领域的未来领导者。该计划每年提供给精选数量的具有领导潜力和多才多艺思维的个人，并欢迎具有不同工作或教育背景的申请人，他们可以帮助RBC以不同的方式思考。理想的申请人是好奇、开放和创新的思想家，他们希望发展动态技能和广泛的经验，以加速他们在 RBC 的职业生涯。</p>          </div><p><img src="../img/Kiki.png" alt=""></p><p>有三种主要的沟通类型：口头沟通、非口头沟通和视觉沟通。<br>在工作场所沟通时，我们需要考虑接收者的角度，确保他们理解我们的意图。<br>自我认知对于有效沟通至关重要，需要了解自己想要传达的信息、目的以及高情商的运用。</p><p>加拿大礼仪在沟通中很重要，身体语言同样重要，人们会根据他人的行为来获取线索。在加拿大文化中，非语言沟通可以通过接受、握手、不看对方等方式进行。在遇到不确定的情况时，可以主动询问，特别是在加拿大这样的多元文化社会中。</p><p>不同文化对于眼神交流和身体语言有不同的解读，加拿大文化中，避免眼神交流可能被认为是不真诚或说谎。</p><p>加拿大文化重视平等主义，而日本文化则具有很高的不确定性规避。权力距离是指有权者和无权者之间的差距，可能存在于父母与子女、上级与下属之间。在加拿大文化中，孩子不允许质疑或反驳父母，而在其他文化中，孩子也不允许质疑或反驳父母。</p><p>在沟通前做好准备，有助于自信地表达自己的观点和目的。</p><p>语言差异是工作场所中最常见的误解之一。沟通是许多人（包括Kiki）在工作中挣扎的问题。加拿大和美国在工作文化上有所不同，加拿大更注重员工福利和健康。Covid-19对每个人的工作产生了影响，并且仍在持续。</p><p>灵活性是远程工作的优势之一，但也改变了我们的工作方式。建议写下自己的想法和语言，并练习积极倾听。注意在提问时的身体语言，不要害怕提问。</p><p>中国不是RBC全球资产管理公司支持远程工作的国家之一。RBC新任CEO希望人们知道他们为什么应该被考虑担任某个职位，并鼓励人们始终用5句话总结自己是谁以及做什么。</p><p>学习唯一的方法是提问，并且不要害怕提问。当有人给你知识时，它永远属于你。他们只能给你一次。了解加拿大最快的方法是与加拿大人交朋友。不要只和看起来像你、说话像你的人交朋友。你需要了解世界，通过了解你的朋友来了解世界。</p><h2 id="第二期的嘉宾-Sasan">第二期的嘉宾 Sasan</h2><h3 id="简介：">简介：</h3><p>Sasan在加拿大PC公司担任参与经理，已经工作了5年，专注于业务转型项。普华永道<sup id="fnref:1" class="footnote-ref"><a href="#fn:1" rel="footnote"><span class="hint--top hint--rounded" aria-label="普华永道在全球152个国家或地区有分支机构，其中包括中国大陆、香港特别行政区和澳门特别行政区。是一家会计师事务所公司，也是世界上最顶级的会计师事务所之一，是国际四大会计师事务所之一1。它的前身是普华会计师事务所和永道会计师事务所，于1998年在英国合并成为现在的普华永道。普华永道的企业使命是建立社会信任和解决重要问题，它为客户提供专业服务，包括审计、税务、咨询等，涵盖多个行业和领域45。它在全球拥有近328,000名专业人员，遍布152个国家或地区。普华永道的企业使命是建立社会信任和解决重要问题，它为客户提供专业服务，包括审计、税务、咨询等，涵盖多个行业和领域45。它在全球拥有近328,000名专业人员，遍布152个国家或地区。">[1]</span></a></sup></p><p>Sasan 在加拿大PC公司与客户合作，确保有效沟通和及时交付。 相关原文: 4页  Sasan Burns在加拿大PC公司强调建立关系和维护关系的重要性，因为公司提供的服务高度依赖人员。<br><img src="../img/Sasan.png" alt=""></p><p>企业正在推动员工回到办公室工作，认为面对面工作有价值。</p><p>成为咨询顾问不需要有商业背景，很多有资格的人可以进入这些公司工作，需要具备良好的解决问题的能力和沟通技能。 相关原文: 12页  面试的关键在于建立人际关系，准备一份强有力的简历，展示实际经验中的技能。</p><p>在家作为咨询顾问工作时，如何解决沟通挑战？   团队规模需要适中，以便进行有效的头脑风暴会议。</p><p>卢西安有多元化的研究背景，研究行业、客户及其运营中的差距。</p><p>背景研究和了解客户问题非常重要，以便向客户展示正确的结果或分析。</p><p>向客户展示结果需要大量的脑力，以便提出易于理解且适合其业务的方案。</p><p>Sasan认为加拿大的工程就业市场非常强劲，并且一直有需求。电气工程具有灵活性，可以向编程和计算机科学方向发展。 LinkedIn是一个非常好的资源，特别是当你不在那个地方时，Sasan说。</p><p>在社交活动中，关系的质量非常重要，同时每个人都应该尊重每个人的界限和任何限制，不能强迫或强加。</p><p>丰田在50或60年前引入了精益运营，以成为全球汽车制造商并获得大量市场份额。精益运营的目标是减少浪费的活动。—》丰田之路（The Toyota Way Fieldbook ）</p><p>上课给的link链接[<a href="https://www.linkedin.com/in/sasanzadeh/?original_referer=https%3A%2F%2Fwww.linkedin.com%2Fin%2Fsasanzadeh%2F%3Foriginal_referer%3D">萨桑·扎德 - 数字运营项目经理 |尤米 |零售与CPG - 普华永道 |LinkedIn</a>]</p><h2 id="第三期的嘉宾-Victor">第三期的嘉宾 Victor</h2><h3 id="嘉宾简介：-v2">嘉宾简介：</h3><p>目前是在TD（多伦多道明银行工作的）<sup id="fnref:2" class="footnote-ref"><a href="#fn:2" rel="footnote"><span class="hint--top hint--rounded" aria-label="TD bank的产品经理是负责开发和管理TD bank的各种金融产品和服务的人员，他们需要具备金融知识、市场分析、项目管理和沟通协调等能力。">[2]</span></a></sup>产品经理<br><img src="../img/Victor.png" alt=""></p><p>沟通中的误解往往是由于信息传递不准确、表达不清或是双方理解不同导致的。为了避免沟通中的误解，可以采取以下几个方法：</p><ol><li>清晰表达：在表达自己的观点或想法时，尽量使用简洁明了、准确无误的语言，避免使用含糊不清或容易引起误解的词汇。</li><li>倾听：认真倾听对方的观点，尽量理解对方的意思，不要急于表达自己的观点。在倾听过程中，可以适时用“嗯”、“哦”等语气词表示自己在认真倾听。</li><li>确认理解：在沟通过程中，适时向对方确认自己是否正确理解了他们的意思。可以使用“您是说……吗？”、“您能再解释一下……吗？”等语句来确认。</li><li>用自己的话复述：在理解对方的观点后，可以尝试用自己的话复述一遍，以确保自己的理解准确无误。</li><li>保持耐心：沟通中难免会出现误解，保持耐心，给双方留出足够的时间和空间来澄清误会。</li><li>了解文化差异：在跨文化沟通中，了解不同文化背景下的沟通习惯和表达方式，有助于减少误解的发生。</li><li>适时反馈：在沟通过程中，可以适时向对方提供反馈，表达自己对某个观点的看法，有助于确保双方的理解一致。</li><li>使用非语言沟通：除了语言沟通外，还可以通过肢体语言、面部表情、眼神交流等非语言方式来传递信息，有助于避免误解的产生。</li><li>沟通频率：保持适当的沟通频率，避免信息不对称导致的误解。</li><li>沟通环境：选择一个安静、舒适的沟通环境，有助于双方保持专注，降低误解的可能性。</li></ol><p>面试是一个展示自己能力和专业素质的机会，所以在面试前做好充分的准备至关重要。以下是一些建议帮助你做好面试准备：</p><ol><li>了解公司：在面试之前，了解应聘公司的基本信息、企业文化、业务范围等，以便在面试中展示你对公司的兴趣和了解。</li><li>研究岗位：仔细阅读招聘广告，了解职位要求，分析自己的技能和经验是否符合要求，并针对性地准备一些问题。</li><li>准备简历：确保简历内容准确、简洁、完整，针对应聘职位突出自己的优势和成就。</li><li>准备自我介绍：准备一个简短的自我介绍，突出自己的教育背景、工作经验、技能和兴趣等，以便在面试中自然地表达。</li><li>准备问题：准备一些关于公司、岗位、团队的问题，以展示你对公司的关注和对工作的热情。</li><li>着装得体：根据公司文化和职位要求，选择合适的着装，给面试官留下良好的第一印象。</li><li>练习面试技巧：了解一些面试技巧，如倾听、沟通、提问、回答等，并在实际面试中进行练习。</li><li>保持良好的心态：面试前保持积极、自信的心态，相信自己能够胜任这个职位。</li><li>提前到达：尽量提前到达面试地点，以便有充足的时间准备和调整状态。</li><li>注意礼仪：面试过程中要保持礼貌、尊重面试官，展示良好的职业素养。</li></ol><div class="note note-success">            <p>虚拟面试：</p><ol><li>准备：在面试或会议前，了解公司和职位信息，准备可能的问题和答案，以及展示自己的优势和价值。</li><li>倾听：在面试或会议中，认真倾听对方的问题和观点，以便更好地理解他们的需求和期望。</li><li>表达：清晰、简洁地表达自己的观点和想法，避免使用过于复杂的词汇和语言。</li><li>提问：在面试或会议中，提出有针对性的问题，以展示自己的专业素养和对话题的关注。</li><li>建立关系：在面试或会议中，展示自己的亲和力和合作精神，以建立良好的人际关系。</li></ol>          </div><p>电梯推销是指在极短的时间内，向潜在客户清晰、简洁地介绍产品或服务，从而达到吸引对方注意力并激发兴趣的目的。电梯推销的目的是在有限的时间内迅速传达关键信息，同时展示产品或服务的优势，以便在竞争激烈的市场中脱颖而出。</p><p>电梯推销的核心原则包括：</p><ol><li>简洁明了：表达要简洁，不要浪费客户的时间。</li><li>突出优势：强调产品或服务的独特卖点，吸引客户的兴趣。</li><li>目标明确：明确推销的目标，是获取客户信息还是促成交易。</li><li>适应场景：根据不同场景调整推销内容，如面对面交流、电话沟通等。<br>电梯推销是一种高效的沟通技巧，适用于销售、市场推广、产品介绍等场景。通过掌握电梯推销技巧，可以提高沟通效率，更好地与客户建立联系。</li></ol><div class="note note-light">            <p>在面试中，要专注于为公司创造价值，避免问关于薪资和假期的问题。<br>提薪酬通常是在面试过程中，面试官主动询问求职者对薪酬的期望，但求职者主动提薪酬会让面试官觉得你只关心薪酬而忽视了公司的发展和工作的意义。此外，如果面试官认为你的能力和经验不足以匹配高薪，主动提薪酬会给面试官留下负面印象。所以，在面试过程中，最好不要主动提薪酬，而是在面试结束后，通过与公司沟通，了解公司的薪酬体系和岗位的薪酬范围，根据自己的能力和期望，给出一个合理的薪酬要求。<br>在面试后，还要感谢面试官花时间与你交流，并表现出对公司的热情。</p>          </div><p>在线存在是一种展示自己观点、想法和与观众互动的好机会。<br>产品经理的工作主要是与人沟通，确定战略和讨论如何实现想法。</p><p>第一印象很重要，但随着时间的推移，人们会逐渐了解你。<br>建立良好的第一印象和关系对于成功至关重要。</p><p>意识到自己不知道的事情，并努力去了解。</p><p>寻求高级职业人士的帮助，建立导师和赞助关系。</p><p>寻找能够为你代言的经理，并利用他们的社会资本。</p><div class="note note-danger">            <p>沟通中的误解是常见的问题，需要避免。<br>沟通中的最大问题是人们认为已经进行了沟通，但实际上并没有。</p>          </div><p>知识不等于经验，银行招聘各种专业的人才。（比如有一位同学询问了作为艺术类专业，毕业工作做有什么建议嘛？嘉宾谈到，可以进银行，银行什么专业的学生都需要） 利用空闲时间进行学习和自我提升。 时间管理对于实现目标至关重要。</p><p>建立人际关系的技能可以应用于工作和学校。</p><p>尊重和沟通可以同时进行。</p><h2 id="第四期嘉宾：Austin">第四期嘉宾：Austin</h2><p><img src="../img/autin.png" alt=""></p><p>Austin是KPMG<sup id="fnref:3" class="footnote-ref"><a href="#fn:3" rel="footnote"><span class="hint--top hint--rounded" aria-label="毕马威（KPMG）是一家国际性的专业服务机构，主要提供审计、税务和咨询等服务。它是世界四大会计师事务所之.与普华永道德勤和安永并列.毕马威的名称来源于其四位创始人的英文缩写Klynveld、Peat、Marwick和Goerdeler。">[3]</span></a></sup>企业绩效管理（EPM）团队的一员，他在KPMG工作了两年多。</p><p>当KPMG的顾问需要学习使用不同的工具，如Excel、Tableau或Sql。</p><p>KPMG正在寻找明年冬天的实习生，不仅在加拿大，还包括美国。</p><p>肢体语言在虚拟环境和面对面环境中都很重要，关键在于你是否清楚地识别了问题。</p><p>KPMG有一个过程，即在会议前确定冠军，以帮助我们更好地准备会议。这个过程包括预客户工作坊、工作坊期间和后客户工作坊。</p><p>在虚拟环境中，有人需要将所有信息整合在一起，确保其可用，因为在虚拟环境中，如果人们连续参加会议，他们可能不会全神贯注。这就是预客户工作坊的工作。</p><p>你想让客户感到他们在参与，并对工作坊中发生的事情负责，通过给他们便签来实现这一点。呈现的方式是在电话会议中，这是你说过的话，这是我对你最初说的话的想法。</p><p>公司有负责危机的团队，他们会发送电子邮件告诉员工应该做什么。这是一般信息，你应该引用它。</p><p>CEO表示，你不必上学就能加入公司，发展核心技能是一个大转变，但发展你的核心技能，他说。个人素质在求职过程中非常重要，包括演讲能力和人际交往能力。</p><p>数据分析能力可以帮助筛选出有用的信息，避免陷入细节。</p><p>KPMG公司注重员工福利，如提供产假和陪产假，并注重员工的表现。 KPMG加拿大公司遵循一套规则和标准，但KPMG中国公司的情况需要进一步了解。</p><p>Chat GPT可以快速生成答案，为团队节省时间。 GPT认为应该将客户和团队成员视为一个团队，共同解决问题。在工作中管理人际关系的方法是首先提问以了解情况，然后与对方的上司沟通。关键是要坦诚地展示自己的日程安排，并理解事情为什么以某种方式完成或表达。通过提问以获得完整的画面，然后进行沟通，了解它如何影响你。</p><p>高级领导和我讨论了发生的事情。当时，我想挂断电话离开，但不幸的是，我不得不在那里再待半个小时。我认为关键是控制自己的情绪，控制自己，控制局面。</p><p>处理数据的两种方法：玩弄数字并组织自己，以及进行实际数据分析，研究哪些工具在客户和其他团队中更受欢迎。</p><p>公司内部有一个基于绩效的评估系统，每个员工都会与其他员工进行比较。但这并不总是最好的。</p><p>我总是喜欢新的挑战，喜欢学习新东西。因为我能够围绕某个主题（如运营）掌握一些东西，但我对深入细节并连续多年工作没有兴趣。 我甚至不知道KPMG的EPM。我只是说，我喜欢看预算和支出。然后我了解了更多关于EPM的信息，他们日常工作做什么。</p><p>我在科学领域，我们专注于细节和埋头苦干。去商学院，我讨厌网络，讨厌演讲，讨厌在观众面前说话。这不是科学家或教授。但我坚持下来，并找到了支持系统。</p><p>花时间找出你的2到3个顶级技能，专注于你的个人品牌和电梯演讲，并走出你的舒适区。我们与Cynthia和Jen合作。也许对你有用？请随时在LinkedIn上联系我。</p><div class="note note-success">            <p>回答问题</p><p>好的，谢谢。是的，这很难，但是，有一种方法可以解决任何问题，了解问题是什么，问题是什么。他们试图实现什么，对吧？有时，当我喜欢浏览成千上万的数据集时。实际上，我把它写在一张纸条上，然后把它贴在我的笔记本电脑上，这样我就可以专注于此。<br>不要迷失在细节中。然后是关于，你知道，你的数据分析方法，比如，一切都有设计。<br>这不仅仅是为了解决问题。首先，你需要明白，你知道，他们为什么要收集这些信息？<br>他们将这些不同类型的信息用于这些不同的数据点是什么？然后，这涉及到与客户合作以获取这些信息。<br>然后你就有了一种方法来分析这些数据，然后开始执行它。<br>所以。在数据分析方面，也有很多关于如何进行的思考，而不仅仅是深入研究数据并将其公布出来。<br>有些人会这样做，这是一个对他们有效的过程。但就我个人而言，当我尝试这样做时，我往往会迷失在数据中，我无法专注于它是什么并进行定义，因为客户只会给你一个数据转储，对吧？<br>他们什么都不做。所以这对我有帮助。</p>          </div><h2 id="总结">总结</h2><p>课程结束了。最后老师给我的评语是：你来上课，你多试了一点，你说话，你在聊天中打字，你的英语越来越强。</p><section class="footnotes"><div class="footnote-list"><ol><li><span id="fn:1" class="footnote-text"><span>普华永道在全球152个国家或地区有分支机构，其中包括中国大陆、香港特别行政区和澳门特别行政区。是一家会计师事务所公司，也是世界上最顶级的会计师事务所之一，是国际四大会计师事务所之一1。它的前身是普华会计师事务所和永道会计师事务所，于1998年在英国合并成为现在的普华永道。普华永道的企业使命是建立社会信任和解决重要问题，它为客户提供专业服务，包括审计、税务、咨询等，涵盖多个行业和领域45。它在全球拥有近328,000名专业人员，遍布152个国家或地区。普华永道的企业使命是建立社会信任和解决重要问题，它为客户提供专业服务，包括审计、税务、咨询等，涵盖多个行业和领域45。它在全球拥有近328,000名专业人员，遍布152个国家或地区。<a href="#fnref:1" rev="footnote" class="footnote-backref"> ↩</a></span></span></li><li><span id="fn:2" class="footnote-text"><span>TD bank的产品经理是负责开发和管理TD bank的各种金融产品和服务的人员，他们需要具备金融知识、市场分析、项目管理和沟通协调等能力。<a href="#fnref:2" rev="footnote" class="footnote-backref"> ↩</a></span></span></li><li><span id="fn:3" class="footnote-text"><span>毕马威（KPMG）是一家国际性的专业服务机构，主要提供审计、税务和咨询等服务。它是世界四大会计师事务所之.与普华永道德勤和安永并列.毕马威的名称来源于其四位创始人的英文缩写Klynveld、Peat、Marwick和Goerdeler。<a href="#fnref:3" rev="footnote" class="footnote-backref"> ↩</a></span></span></li></ol></div></section>]]></content>
    
    
    
  </entry>
  
  
  
  <entry>
    <title>我的第一个博客</title>
    <link href="/weilai.github.io/2023/06/29/%E6%88%91%E7%9A%84%E7%AC%AC%E4%B8%80%E4%B8%AA%E5%8D%9A%E5%AE%A2/"/>
    <url>/weilai.github.io/2023/06/29/%E6%88%91%E7%9A%84%E7%AC%AC%E4%B8%80%E4%B8%AA%E5%8D%9A%E5%AE%A2/</url>
    
    <content type="html"><![CDATA[<h1>标题</h1><h3 id=""></h3><figure class="highlight c++"><table><tr><td class="gutter"><pre><span class="line">1</span><br><span class="line">2</span><br></pre></td><td class="code"><pre><code class="hljs c++"><span class="hljs-meta">#<span class="hljs-keyword">include</span> <span class="hljs-string">&lt;stdio.h&gt;</span></span><br><span class="hljs-keyword">using</span> <span class="hljs-keyword">namespace</span> std;<br></code></pre></td></tr></table></figure><p><a href="baidu.com%22%E4%B8%80%E4%B8%AA%E6%90%9C%E7%B4%A2%E5%BC%95%E6%93%8E%22">百度</a></p><hr><p>😄</p><h2 id="标题2">标题2</h2><h3 id="-v2"></h3><p>个人博客<sup id="fnref:1" class="footnote-ref"><a href="#fn:1" rel="footnote"><span class="hint--top hint--rounded" aria-label="欢迎光临我的博客*斜体*   **加粗**  下划线  国际通用表情 :smile: (https://unicode.org/emoji/charts/full-emoji-list.html):grinning:  :wink:">[1]</span></a></sup></p><p>url:<br><a href="https://qiantubu.github.io/weilai.github.io/">https://qiantubu.github.io/weilai.github.io/</a></p><p>![好图分享](<a href="https://qiantubu.github.io/weilai.github.io/img/1.gif">1.gif (768×432) (qiantubu.github.io)</a>)</p><hr><hr><p>标题3</p><p><mjx-container class="MathJax" jax="SVG"><svg style="vertical-align: -0.186ex;" xmlns="http://www.w3.org/2000/svg" width="6.36ex" height="2.072ex" role="img" focusable="false" viewBox="0 -833.9 2811.1 915.9"><g stroke="currentColor" fill="currentColor" stroke-width="0" transform="scale(1,-1)"><g data-mml-node="math"><g data-mml-node="mi"><path data-c="1D703" d="M35 200Q35 302 74 415T180 610T319 704Q320 704 327 704T339 705Q393 701 423 656Q462 596 462 495Q462 380 417 261T302 66T168 -10H161Q125 -10 99 10T60 63T41 130T35 200ZM383 566Q383 668 330 668Q294 668 260 623T204 521T170 421T157 371Q206 370 254 370L351 371Q352 372 359 404T375 484T383 566ZM113 132Q113 26 166 26Q181 26 198 36T239 74T287 161T335 307L340 324H145Q145 321 136 286T120 208T113 132Z"></path></g><g data-mml-node="mo" transform="translate(746.8,0)"><path data-c="3D" d="M56 347Q56 360 70 367H707Q722 359 722 347Q722 336 708 328L390 327H72Q56 332 56 347ZM56 153Q56 168 72 173H708Q722 163 722 153Q722 140 707 133H70Q56 140 56 153Z"></path></g><g data-mml-node="msup" transform="translate(1802.6,0)"><g data-mml-node="mi"><path data-c="1D465" d="M52 289Q59 331 106 386T222 442Q257 442 286 424T329 379Q371 442 430 442Q467 442 494 420T522 361Q522 332 508 314T481 292T458 288Q439 288 427 299T415 328Q415 374 465 391Q454 404 425 404Q412 404 406 402Q368 386 350 336Q290 115 290 78Q290 50 306 38T341 26Q378 26 414 59T463 140Q466 150 469 151T485 153H489Q504 153 504 145Q504 144 502 134Q486 77 440 33T333 -11Q263 -11 227 52Q186 -10 133 -10H127Q78 -10 57 16T35 71Q35 103 54 123T99 143Q142 143 142 101Q142 81 130 66T107 46T94 41L91 40Q91 39 97 36T113 29T132 26Q168 26 194 71Q203 87 217 139T245 247T261 313Q266 340 266 352Q266 380 251 392T217 404Q177 404 142 372T93 290Q91 281 88 280T72 278H58Q52 284 52 289Z"></path></g><g data-mml-node="mn" transform="translate(605,363) scale(0.707)"><path data-c="32" d="M109 429Q82 429 66 447T50 491Q50 562 103 614T235 666Q326 666 387 610T449 465Q449 422 429 383T381 315T301 241Q265 210 201 149L142 93L218 92Q375 92 385 97Q392 99 409 186V189H449V186Q448 183 436 95T421 3V0H50V19V31Q50 38 56 46T86 81Q115 113 136 137Q145 147 170 174T204 211T233 244T261 278T284 308T305 340T320 369T333 401T340 431T343 464Q343 527 309 573T212 619Q179 619 154 602T119 569T109 550Q109 549 114 549Q132 549 151 535T170 489Q170 464 154 447T109 429Z"></path></g></g></g></g></svg></mjx-container><br>H<sub>2</sub>O ,X<sup>2</sup><br>==高亮文字==</p><iframe src="//player.bilibili.com/player.html?aid=327623069&bvid=BV1JA411h7Gw&cid=171385214&page=1" scrolling="no" border="0" frameborder="no" framespacing="0" allowfullscreen="true"> </iframe><p>嵌入视频代码</p><p>使用QT WebAssembly生成的时钟</p><p>🤩（<a href="https://qiantubu.github.io/WebAssembly_analogclock.github.io/analogclock/analogclock.html">analogclock (qiantubu.github.io)</a>）</p><section class="footnotes"><div class="footnote-list"><ol><li><span id="fn:1" class="footnote-text"><span>欢迎光临我的博客<br><em>斜体</em>   <strong>加粗</strong>  <u>下划线</u><br>国际通用表情 😄 (<a href="https://unicode.org/emoji/charts/full-emoji-list.html">https://unicode.org/emoji/charts/full-emoji-list.html</a>)<br>😀  😉<a href="#fnref:1" rev="footnote" class="footnote-backref"> ↩</a></span></span></li></ol></div></section>]]></content>
    
    
    
  </entry>
  
  
  
  <entry>
    <title>我的口语学习记录</title>
    <link href="/weilai.github.io/2023/06/29/%E8%8B%B1%E8%AF%AD%E5%8F%A3%E8%AF%AD%E5%AD%A6%E4%B9%A0%E8%AE%B0%E5%BD%95/"/>
    <url>/weilai.github.io/2023/06/29/%E8%8B%B1%E8%AF%AD%E5%8F%A3%E8%AF%AD%E5%AD%A6%E4%B9%A0%E8%AE%B0%E5%BD%95/</url>
    
    <content type="html"><![CDATA[<p>这里是英语口语学习记录：</p><h4 id="第一次课-2023-7-10">第一次课 2023.7.10</h4><p>鼓励他人讲述很好：</p><div class="note note-success">            <p>伙计们，活儿不错！干得好！<br>Good work, guys! Way to go! 😄</p>          </div><p>线上交流，可以先说：</p><div class="note note-success">            <p>大家好呀！能听到我说话嘛？<br>Hi everyone,  can you hear me? 🥰</p>          </div><hr><h4 id="第二次课-2023-7-12">第二次课 2023.7.12</h4><p>表示参与到这个，深感荣幸，不用honor,用pleasure!</p>]]></content>
    
    
    
  </entry>
  
  
  
  <entry>
    <title>Hello World</title>
    <link href="/weilai.github.io/2023/06/28/hello-world/"/>
    <url>/weilai.github.io/2023/06/28/hello-world/</url>
    
    <content type="html"><![CDATA[<p>Welcome to <a href="https://hexo.io/">Hexo</a>! This is your very first post. Check <a href="https://hexo.io/docs/">documentation</a> for more info. If you get any problems when using Hexo, you can find the answer in <a href="https://hexo.io/docs/troubleshooting.html">troubleshooting</a> or you can ask me on <a href="https://github.com/hexojs/hexo/issues">GitHub</a>.</p><h2 id="Quick-Start"><a href="#Quick-Start" class="headerlink" title="Quick Start"></a>Quick Start</h2><h3 id="Create-a-new-post"><a href="#Create-a-new-post" class="headerlink" title="Create a new post"></a>Create a new post</h3><figure class="highlight bash"><table><tr><td class="gutter"><pre><span class="line">1</span><br></pre></td><td class="code"><pre><span class="line">$ hexo new <span class="string">&quot;My New Post&quot;</span></span><br></pre></td></tr></table></figure><p>More info: <a href="https://hexo.io/docs/writing.html">Writing</a></p><h3 id="Run-server"><a href="#Run-server" class="headerlink" title="Run server"></a>Run server</h3><figure class="highlight bash"><table><tr><td class="gutter"><pre><span class="line">1</span><br></pre></td><td class="code"><pre><span class="line">$ hexo server</span><br></pre></td></tr></table></figure><p>More info: <a href="https://hexo.io/docs/server.html">Server</a></p><h3 id="Generate-static-files"><a href="#Generate-static-files" class="headerlink" title="Generate static files"></a>Generate static files</h3><figure class="highlight bash"><table><tr><td class="gutter"><pre><span class="line">1</span><br></pre></td><td class="code"><pre><span class="line">$ hexo generate</span><br></pre></td></tr></table></figure><p>More info: <a href="https://hexo.io/docs/generating.html">Generating</a></p><h3 id="Deploy-to-remote-sites"><a href="#Deploy-to-remote-sites" class="headerlink" title="Deploy to remote sites"></a>Deploy to remote sites</h3><figure class="highlight bash"><table><tr><td class="gutter"><pre><span class="line">1</span><br></pre></td><td class="code"><pre><span class="line">$ hexo deploy</span><br></pre></td></tr></table></figure><p>More info: <a href="https://hexo.io/docs/one-command-deployment.html">Deployment</a></p>]]></content>
    
    
    
  </entry>
  
  
  
  
</search>
